{"_ts":[1497957198,1497957335],"_r":{"breakdown":{"html":{"bytes":[63515,62463],"requests":[18,15]},"js":{"bytes":[512848,561016],"requests":[35,35]},"css":{"bytes":[140445,140445],"requests":[3,3]},"image":{"bytes":[834812,834332],"requests":[53,52]},"flash":{"bytes":[0,0],"requests":[0,0]},"font":{"bytes":[58234,58234],"requests":[4,4]},"other":{"bytes":[5797,5799],"requests":[6,6]}},"date":[1497957198,1497957335],"domElements":[2539,2538],"domInteractive":[2035,1541],"firstPaint":[977,1008],"fullyLoaded":[6665,6963],"id":["170620_GY_2","170620_21_3"],"loadTime":[4990,4732],"render":[1179,1173],"SpeedIndex":[2833,2332],"TTFB":[455,437],"videoFrames":[[{"_i":"frame_0000.jpg","_t":0,"_vc":0},{"_i":"frame_0012.jpg","_t":1200,"_vc":3},{"_i":"frame_0014.jpg","_t":1400,"_vc":9},{"_i":"frame_0015.jpg","_t":1500,"_vc":13},{"_i":"frame_0016.jpg","_t":1600,"_vc":14},{"_i":"frame_0018.jpg","_t":1800,"_vc":14},{"_i":"frame_0022.jpg","_t":2200,"_vc":14},{"_i":"frame_0026.jpg","_t":2600,"_vc":16},{"_i":"frame_0028.jpg","_t":2800,"_vc":90},{"_i":"frame_0054.jpg","_t":5400,"_vc":100}],[{"_i":"frame_0000.jpg","_t":0,"_vc":0},{"_i":"frame_0012.jpg","_t":1200,"_vc":3},{"_i":"frame_0015.jpg","_t":1500,"_vc":9},{"_i":"frame_0017.jpg","_t":1700,"_vc":9},{"_i":"frame_0018.jpg","_t":1800,"_vc":14},{"_i":"frame_0022.jpg","_t":2200,"_vc":88},{"_i":"frame_0028.jpg","_t":2800,"_vc":90},{"_i":"frame_0044.jpg","_t":4400,"_vc":91},{"_i":"frame_0046.jpg","_t":4600,"_vc":100}]],"visualComplete":[5394,4570],"lighthouse":[null,null],"pagespeed":[71,71]}}